.gitignore
MANIFEST.in
README.rst
base.cfg
bootstrap.py
buildout.cfg
development.cfg
pre-commit-check.sh
setup.cfg
setup.py
versions.cfg
docs/HISTORY.rst
docs/LICENSE.rst
docs/README.rst
docs/api.rst
docs/conf.py
docs/glossary.rst
docs/index.rst
docs/translations.rst
src/iwwb/__init__.py
src/iwwb.eventlist.egg-info/PKG-INFO
src/iwwb.eventlist.egg-info/SOURCES.txt
src/iwwb.eventlist.egg-info/dependency_links.txt
src/iwwb.eventlist.egg-info/entry_points.txt
src/iwwb.eventlist.egg-info/namespace_packages.txt
src/iwwb.eventlist.egg-info/not-zip-safe
src/iwwb.eventlist.egg-info/requires.txt
src/iwwb.eventlist.egg-info/top_level.txt
src/iwwb/eventlist/__init__.py
src/iwwb/eventlist/config.py
src/iwwb/eventlist/configure.zcml
src/iwwb/eventlist/interfaces.py
src/iwwb/eventlist/searcher.py
src/iwwb/eventlist/version.txt
src/iwwb/eventlist/vocabularies.py
src/iwwb/eventlist/browser/__init__.py
src/iwwb/eventlist/browser/configure.zcml
src/iwwb/eventlist/browser/eventlist.pt
src/iwwb/eventlist/browser/eventlist.py
src/iwwb/eventlist/browser/proxy.py
src/iwwb/eventlist/browser/zipcode.pt
src/iwwb/eventlist/browser/resources/dataTables.english.txt
src/iwwb/eventlist/browser/resources/dataTables.german.txt
src/iwwb/eventlist/browser/resources/eventlist.css
src/iwwb/eventlist/browser/resources/eventlist.js
src/iwwb/eventlist/browser/resources/germany_map.gif
src/iwwb/eventlist/browser/resources/overlay_close.png
src/iwwb/eventlist/locales/iwwb.eventlist.pot
src/iwwb/eventlist/locales/de/LC_MESSAGES/iwwb.eventlist.po
src/iwwb/eventlist/profiles/default/browserlayer.xml
src/iwwb/eventlist/profiles/default/metadata.xml
src/iwwb/eventlist/tests/__init__.py
src/iwwb/eventlist/tests/base.py
src/iwwb/eventlist/tests/test_searcher.py
src/iwwb/eventlist/tests/test_setup.py