Metadata-Version: 1.0
Name: iwwb.eventlist
Version: 0.2
Summary: Enter description of what this project is all about.
Home-page: http://www.niteoweb.com
Author: NiteoWeb Ltd.
Author-email: info@niteoweb.com
License: BSD
Keywords: Plone Python
Platform: UNKNOWN
Classifier: Framework :: Plone
Classifier: Programming Language :: Python
